xio/__init__.py
xio/__init__.pyc
xio/.pytest_cache/.gitignore
xio/.pytest_cache/README.md
xio/.pytest_cache/v/cache/lastfailed
xio/.pytest_cache/v/cache/nodeids
xio/.pytest_cache/v/cache/stepwise
xio/__pycache__/__init__.cpython-37.pyc
xio/core/__init__.py
xio/core/__init__.pyc
xio/core/env.py
xio/core/env.pyc
xio/core/handlers.py
xio/core/peer.py
xio/core/peers.py
xio/core/request.py
xio/core/request.pyc
xio/core/resource.py
xio/core/user.py
xio/core/utils.py
xio/core/__pycache__/__init__.cpython-37.pyc
xio/core/__pycache__/env.cpython-37.pyc
xio/core/__pycache__/handlers.cpython-37.pyc
xio/core/__pycache__/peer.cpython-37.pyc
xio/core/__pycache__/peers.cpython-37.pyc
xio/core/__pycache__/request.cpython-37.pyc
xio/core/__pycache__/resource.cpython-37.pyc
xio/core/__pycache__/user.cpython-37.pyc
xio/core/__pycache__/utils.cpython-37.pyc
xio/core/app/__init__.py
xio/core/app/admin.py
xio/core/app/app.py
xio/core/app/__pycache__/__init__.cpython-37.pyc
xio/core/app/__pycache__/app.cpython-37.pyc
xio/core/app/lib/__init__.py
xio/core/app/lib/cache.py
xio/core/app/lib/cron.py
xio/core/app/lib/http.py
xio/core/app/lib/pubsub.py
xio/core/app/lib/stats.py
xio/core/app/lib/tasks.py
xio/core/app/lib/websocket.py
xio/core/app/tests/__init__.py
xio/core/app/tests/test_app.py
xio/core/app/tests/test_services.py
xio/core/app/tests/apptest/__init__.py
xio/core/app/tests/apptest/about.yml
xio/core/app/tests/apptest/app.py
xio/core/app/tests/apptest/tests.py
xio/core/app/tests/apptest/ext/appext/__init__.py
xio/core/app/tests/apptest/ext/appext/about.yml
xio/core/app/tests/apptest/ext/appext/app.py
xio/core/app/tests/apptest/www/index.html
xio/core/app/tests/apptest/www/static/test.json
xio/core/app/tests/apptest/www/static/test.md
xio/core/lib/__init__.py
xio/core/lib/__init__.pyc
xio/core/lib/logs.py
xio/core/lib/logs.pyc
xio/core/lib/utils.py
xio/core/lib/utils.pyc
xio/core/lib/__pycache__/__init__.cpython-37.pyc
xio/core/lib/__pycache__/logs.cpython-37.pyc
xio-0.0.6.dist-info/LICENSE.txt
xio-0.0.6.dist-info/METADATA
xio-0.0.6.dist-info/WHEEL
xio-0.0.6.dist-info/top_level.txt
xio-0.0.6.dist-info/RECORD
