Metadata-Version: 2.1
Name: xio
Version: 0.0.6
Summary: simple microframework for microservices rapid prototyping
Home-page: https://github.com/inxio/xio
Author: Ludovic Jacquelin
Author-email: ludovic.jacquelin@gmail.com
License: MIT
Keywords: microframework microservices prototyping
Platform: UNKNOWN
Classifier: Development Status :: 3 - Alpha
Classifier: Intended Audience :: Developers
Classifier: License :: OSI Approved :: MIT License
Classifier: Natural Language :: English
Classifier: Programming Language :: Python :: 2.7
Classifier: Programming Language :: Python :: 3
Classifier: Programming Language :: Python :: 3.5
Classifier: Programming Language :: Python :: 3.6
Requires-Python: >=3.5.*
Requires-Dist: requests
Requires-Dist: pyyaml
Requires-Dist: pynacl
Requires-Dist: ws4py
Requires-Dist: ethereum ; python_version < "3.0"
Requires-Dist: eth-typing (<2) ; python_version > "3.0"
Requires-Dist: web3 (>4.8) ; python_version > "3.0"
Provides-Extra: server
Requires-Dist: gevent ; extra == 'server'
Requires-Dist: uswgi ; extra == 'server'
